csvio/__init__.py
csvio/csvbase.py
csvio/csvreader.py
csvio/csvwriter.py
csvio/errors.py
csvio/filebase.py
csvio/processors/__init__.py
csvio/processors/field_processor.py
csvio/processors/processor_base.py
csvio/processors/row_processor.py
csvio/remote/__init__.py
csvio/remote/ftp.py
csvio/remote/remote_base.py
csvio/utils/__init__.py
csvio/utils/types.py
csvio-1.1.2.dist-info/LICENSE
csvio-1.1.2.dist-info/WHEEL
csvio-1.1.2.dist-info/METADATA
csvio-1.1.2.dist-info/RECORD
