Metadata-Version: 2.1
Name: csvio
Version: 1.1.2
Summary: CSV Wrapper for conveniently processing csv files
Home-page: https://csvio.readthedocs.io
License: MIT
Keywords: csv,file processing,utilities,python
Author: Salman Raza
Author-email: raza.salman@gmail.com
Requires-Python: >=3.8,<4.0
Classifier: Environment :: Console
Classifier: License :: OSI Approved :: MIT License
Classifier: Operating System :: OS Independent
Classifier: Programming Language :: Python :: 3
Classifier: Programming Language :: Python :: 3.10
Classifier: Programming Language :: Python :: 3.8
Classifier: Programming Language :: Python :: 3.9
Classifier: Topic :: Software Development :: Libraries :: Python Modules
Classifier: Topic :: Text Processing
Classifier: Topic :: Text Processing :: General
Classifier: Topic :: Utilities
Project-URL: Documentation, https://csvio.readthedocs.io
Project-URL: Repository, https://github.com/s-raza/csvio
